fetchfox/__init__.py
fetchfox/apis/__init__.py
fetchfox/apis/algorand/__init__.py
fetchfox/apis/algorand/algonodecloud/__init__.py
fetchfox/apis/algorand/algonodecloud/accounts.py
fetchfox/apis/algorand/algonodecloud/assets.py
fetchfox/apis/algorand/algonodecloud/common.py
fetchfox/apis/algorand/algonodecloud/schemas.py
fetchfox/apis/algorand/nfdomains/__init__.py
fetchfox/apis/algorand/nfdomains/common.py
fetchfox/apis/algorand/nfdomains/nfd.py
fetchfox/apis/algorand/randswapcom/__init__.py
fetchfox/apis/algorand/randswapcom/common.py
fetchfox/apis/algorand/randswapcom/creator.py
fetchfox/apis/algorand/randswapcom/schemas.py
fetchfox/apis/base.py
fetchfox/apis/cardano/__init__.py
fetchfox/apis/cardano/dexhunterio/__init__.py
fetchfox/apis/cardano/dexhunterio/assets.py
fetchfox/apis/cardano/dexhunterio/common.py
fetchfox/apis/cardano/dexhunterio/constants.py
fetchfox/apis/cardano/gomaestroorg/__init__.py
fetchfox/apis/cardano/gomaestroorg/accounts.py
fetchfox/apis/cardano/gomaestroorg/addresses.py
fetchfox/apis/cardano/gomaestroorg/assets.py
fetchfox/apis/cardano/gomaestroorg/common.py
fetchfox/apis/cardano/gomaestroorg/handles.py
fetchfox/apis/cardano/gomaestroorg/policies.py
fetchfox/apis/cardano/gomaestroorg/pools.py
fetchfox/apis/cardano/gomaestroorg/schemas.py
fetchfox/apis/cardano/gomaestroorg/transactions.py
fetchfox/apis/cardano/jpgstore/__init__.py
fetchfox/apis/cardano/jpgstore/collections.py
fetchfox/apis/cardano/jpgstore/common.py
fetchfox/apis/cardano/jpgstore/policies.py
fetchfox/apis/cardano/jpgstore/schemas.py
fetchfox/apis/coingeckocom/__init__.py
fetchfox/apis/coingeckocom/coins.py
fetchfox/apis/coingeckocom/common.py
fetchfox/apis/coingeckocom/schemas.py
fetchfox/apis/evm/__init__.py
fetchfox/apis/evm/ensideascom/__init__.py
fetchfox/apis/evm/ensideascom/common.py
fetchfox/apis/evm/ensideascom/ens.py
fetchfox/apis/evm/moralisio/__init__.py
fetchfox/apis/evm/moralisio/addresses.py
fetchfox/apis/evm/moralisio/assets.py
bookio_fetchfox-6.0.2.dist-info/WHEEL
bookio_fetchfox-6.0.2.dist-info/METADATA
bookio_fetchfox-6.0.2.dist-info/RECORD
