Metadata-Version: 2.1
Name: bookio-fetchfox
Version: 6.0.2
Summary: Collection of API services to fetch information from several blockchains.
Home-page: https://github.com/book-io/fetchfox
License: MIT
Keywords: book.io,stuff.io,blockchain,crypto,algorand,cardano,coinbase,ethereum,polygon
Author: Fede
Author-email: fede@book.io
Requires-Python: >=3.9,<4.0
Classifier: Intended Audience :: Developers
Classifier: License :: OSI Approved :: MIT License
Classifier: Programming Language :: Python :: 3
Classifier: Programming Language :: Python :: 3.9
Classifier: Programming Language :: Python :: 3.10
Classifier: Programming Language :: Python :: 3.11
Classifier: Programming Language :: Python :: 3.10
Classifier: Programming Language :: Python :: 3.11
Classifier: Programming Language :: Python :: 3.12
Classifier: Programming Language :: Python :: 3.9
Requires-Dist: aiohttp (>=3.12.15,<4.0.0)
Requires-Dist: asyncio (>=4.0.0,<5.0.0)
Requires-Dist: backoff (>=2.2.1,<3.0.0)
Requires-Dist: cachetools (>=5.3.3,<6.0.0)
Requires-Dist: certifi (>=2025.8.3,<2026.0.0)
Requires-Dist: poetry-core (>=2.1.3,<3.0.0)
Requires-Dist: pydantic (>=2.11.7,<3.0.0)
Requires-Dist: pytz (>=2025.2,<2026.0)
Project-URL: Documentation, https://github.com/book-io/fetchfox/blob/main/README.md
